{"MsgID":3,"PacketSize":670,"ID":"3","Password":"3","GoldAmount":1500,"TokenCount":2000,"MainCharacters":[{"ChID":1,"ChLevel":1,"ChHp":100,"ChDamage":80,"ChArmor":2,"ChSpd":2},{"ChID":2,"ChLevel":1,"ChHp":150,"ChDamage":60,"ChArmor":1,"ChSpd":1},{"ChID":3,"ChLevel":1,"ChHp":200,"ChDamage":40,"ChArmor":5,"ChSpd":5}],"CharacterCount":0,"OwnedCharacters":[{"ChID":45048,"ChLevel":26726,"ChHp":386,"ChDamage":0,"ChArmor":0,"ChSpd":0},{"ChID":0,"ChLevel":0,"ChHp":0,"ChDamage":0,"ChArmor":0,"ChSpd":0},{"ChID":0,"ChLevel":0,"ChHp":0,"ChDamage":0,"ChArmor":13176,"ChSpd":35811},{"ChID":386,"ChLevel":0,"ChHp":0,"ChDamage":0,"ChArmor":0,"ChSpd":0},{"ChID":3,"ChLevel":0,"ChHp":0,"ChDamage":0,"ChArmor":0,"ChSpd":0},{"ChID":0,"ChLevel":0,"ChHp":13176,"ChDamage":35811,"ChArmor":386,"ChSpd":0},{"ChID":0,"ChLevel":0,"ChHp":0,"ChDamage":0,"ChArmor":2,"ChSpd":0},{"ChID":0,"ChLevel":0,"ChHp":0,"ChDamage":0,"ChArmor":0,"ChSpd":0},{"ChID":13176,"ChLevel":35811,"ChHp":386,"ChDamage":0,"ChArmor":0,"ChSpd":0},{"ChID":0,"ChLevel":0,"ChHp":1,"ChDamage":0,"ChArmor":0,"ChSpd":0},{"ChID":0,"ChLevel":0,"ChHp":0,"ChDamage":0,"ChArmor":8808,"ChSpd":8235},{"ChID":386,"ChLevel":0,"ChHp":0,"ChDamage":0,"ChArmor":0,"ChSpd":0},{"ChID":1,"ChLevel":0,"ChHp":51,"ChDamage":0,"ChArmor":0,"ChSpd":0},{"ChID":0,"ChLevel":0,"ChHp":8808,"ChDamage":8235,"ChArmor":386,"ChSpd":0},{"ChID":0,"ChLevel":0,"ChHp":0,"ChDamage":0,"ChArmor":4,"ChSpd":0},{"ChID":76,"ChLevel":118,"ChHp":46,"ChDamage":49,"ChArmor":0,"ChSpd":0},{"ChID":8808,"ChLevel":8235,"ChHp":386,"ChDamage":0,"ChArmor":0,"ChSpd":0},{"ChID":0,"ChLevel":0,"ChHp":1,"ChDamage":0,"ChArmor":49,"ChSpd":0},{"ChID":0,"ChLevel":0,"ChHp":0,"ChDamage":0,"ChArmor":8808,"ChSpd":8235},{"ChID":386,"ChLevel":0,"ChHp":0,"ChDamage":0,"ChArmor":0,"ChSpd":0},{"ChID":1,"ChLevel":0,"ChHp":50,"ChDamage":0,"ChArmor":0,"ChSpd":0},{"ChID":0,"ChLevel":0,"ChHp":8808,"ChDamage":8235,"ChArmor":386,"ChSpd":0},{"ChID":0,"ChLevel":0,"ChHp":0,"ChDamage":0,"ChArmor":4,"ChSpd":0},{"ChID":76,"ChLevel":118,"ChHp":46,"ChDamage":49,"ChArmor":0,"ChSpd":0},{"ChID":8808,"ChLevel":8235,"ChHp":386,"ChDamage":0,"ChArmor":0,"ChSpd":0},{"ChID":0,"ChLevel":0,"ChHp":1,"ChDamage":0,"ChArmor":49,"ChSpd":0},{"ChID":0,"ChLevel":0,"ChHp":0,"ChDamage":0,"ChArmor":8808,"ChSpd":8235},{"ChID":386,"ChLevel":0,"ChHp":0,"ChDamage":0,"ChArmor":0,"ChSpd":0},{"ChID":1,"ChLevel":0,"ChHp":49,"ChDamage":0,"ChArmor":0,"ChSpd":0},{"ChID":0,"ChLevel":0,"ChHp":8808,"ChDamage":8235,"ChArmor":386,"ChSpd":0},{"ChID":0,"ChLevel":0,"ChHp":0,"ChDamage":0,"ChArmor":4,"ChSpd":0},{"ChID":76,"ChLevel":118,"ChHp":46,"ChDamage":49,"ChArmor":0,"ChSpd":0},{"ChID":8808,"ChLevel":8235,"ChHp":386,"ChDamage":0,"ChArmor":0,"ChSpd":0},{"ChID":0,"ChLevel":0,"ChHp":1,"ChDamage":0,"ChArmor":49,"ChSpd":0},{"ChID":0,"ChLevel":0,"ChHp":0,"ChDamage":0,"ChArmor":13176,"ChSpd":35811},{"ChID":386,"ChLevel":0,"ChHp":0,"ChDamage":0,"ChArmor":0,"ChSpd":0},{"ChID":3,"ChLevel":0,"ChHp":0,"ChDamage":0,"ChArmor":0,"ChSpd":0},{"ChID":0,"ChLevel":0,"ChHp":13176,"ChDamage":35811,"ChArmor":386,"ChSpd":0},{"ChID":0,"ChLevel":0,"ChHp":0,"ChDamage":0,"ChArmor":2,"ChSpd":0},{"ChID":0,"ChLevel":0,"ChHp":0,"ChDamage":0,"ChArmor":0,"ChSpd":0},{"ChID":13176,"ChLevel":35811,"ChHp":386,"ChDamage":0,"ChArmor":0,"ChSpd":0},{"ChID":0,"ChLevel":0,"ChHp":1,"ChDamage":0,"ChArmor":0,"ChSpd":0},{"ChID":0,"ChLevel":0,"ChHp":0,"ChDamage":0,"ChArmor":8808,"ChSpd":8235},{"ChID":386,"ChLevel":0,"ChHp":0,"ChDamage":0,"ChArmor":0,"ChSpd":0},{"ChID":4,"ChLevel":0,"ChHp":50,"ChDamage":48,"ChArmor":48,"ChSpd":48},{"ChID":0,"ChLevel":0,"ChHp":8808,"ChDamage":8235,"ChArmor":386,"ChSpd":0},{"ChID":0,"ChLevel":0,"ChHp":0,"ChDamage":0,"ChArmor":4,"ChSpd":0},{"ChID":49,"ChLevel":53,"ChHp":48,"ChDamage":48,"ChArmor":0,"ChSpd":0},{"ChID":24528,"ChLevel":35755,"ChHp":386,"ChDamage":0,"ChArmor":0,"ChSpd":0},{"ChID":0,"ChLevel":0,"ChHp":20176,"ChDamage":8413,"ChArmor":385,"ChSpd":0}]}